{
  "name": "Jay Curtis",
  "age": 31,
  "address": {
    "street": "Mehah Ridge",
    "city": "Arrirog",
    "state": "SD",
    "zip": "89200"
  },
  "contact": {
    "phone": "(919) 975-2993",
    "servicePhone": "800469775"
  },
  "birthday": "2002-02-23T23:01:08.134Z",
  "ip": "176.167.68.192",
  "foo": "bar",
  "profile": {
    "about": "Us bi won immo ila wahpeeda kingaju so javopip ru sordepu ev. Eluuwrev tuted cotuje seril lajolwi nawaaj od reemezi gavnetvu hoz mil be gojaub moc tuerade aztu nivtukko esmof. Gurveoz damkan cap pijzadij migik rev dutaz irafe vowvof bes vaalo jawgod faofigiz poboj nukuuc bafi zez. Wu favgezo cokjibso lajpu wo tabi winurgac avaci ab macal bi ji kuheg cumoger vevpafib vudwoid tihor. Majpihuw amja zi kav dutgel gus sugnet jazca tuva lig cabufsol luuneje wafpom ofuwi dipvaza ha nudelte. Zirlob pefzok ursudir zucleh bakhofoto puc fe gudrodib leje wevfezov kabnige wihte rupohvuw paeh tej jegro kevion. Jigbubuh lezre vagof wussewvud eca dik ku ciggucciv lu awo kupoh upu.",
    "bio": "Ajfoju seltehi lugevguz irejo pav voddozgat veiki nis ces woh iwevaaw dajo iwato cagute caf. Erze ame hozug nif gelejru jeeci tipocjed mad gucup vejpofrec gac ig sulod. Onjuj ojame zonfowu ram mos norel lak ze zachubmop digocho ik jo pek batrin kaehi kozuku. Niwjow embav woghu so to oj lospem sif gu vifcisga jal wulwaba aje joldacju gatasawuf oz."
  },
  "apiKey": "c54138f142b49207fb6ba15147a8439f5f0edeeea1a0e48d6f13ddc3141d2ea7",
  "currency": {
    "code": "KWD",
    "name": "Kuwait Dinar"
  }
}